cryptpy-0.3.7.dist-info/METADATA
cryptpy-0.3.7.dist-info/RECORD
cryptpy-0.3.7.dist-info/WHEEL
cryptpy-0.3.7.dist-info/entry_points.txt
cryptpy-0.3.7.dist-info/top_level.txt
src/__init__.py
src/main.py
src/bot/__init__.py
src/bot/bot.py
src/bot/bot_test.py
src/command/__init__.py
src/command/command.py
src/command/command_test.py
src/common/__init__.py
src/common/common.py
src/common/commondefs.py
src/common/commonio.py
src/common/portforwardlib.py
src/database/__init__.py
src/database/database.py
src/database/database_test.py
src/networking/__init__.py
src/networking/client.py
src/networking/client_test.py
src/networking/server.py
src/networking/server_test.py
