Metadata-Version: 2.1
Name: cryptpy
Version: 0.3.7
Summary: Dynamically programmable Python/JS botnet (educational purposes only).
Home-page: https://github.com/mitsukomegumi/CryptPy.js
Author: Mitsuko Megumi, Matt Nappo
Author-email: mitsukomegumii@gmail.com
License: UNKNOWN
Project-URL: Bug Reports, https://github.com/mitsukomegumi/CryptPy.js/issues
Project-URL: Say Thanks!, https://saythanks.io/to/mitsukomegumi
Project-URL: Source, https://github.com/mitsukomegumi/CryptPy.js/
Keywords: botnet tools development python js javascript hacking hackerman imin
Platform: UNKNOWN
Classifier: Development Status :: 3 - Alpha
Classifier: Intended Audience :: Developers
Classifier: License :: OSI Approved :: GNU General Public License v3 (GPLv3)
Classifier: Programming Language :: Python :: 3
Classifier: Programming Language :: Python :: 3.4
Classifier: Programming Language :: Python :: 3.5
Classifier: Programming Language :: Python :: 3.6
Requires-Dist: ipgetter
Requires-Dist: py3-rest-shell
Requires-Dist: simplejson
